{
  "Aleutians East": {
    "dateStr": "11/25/21",
    "cases": 449,
    "deaths": 3,
    "recovered": 0,
    "new": 0,
    "newDeaths": 0
  },
  "Aleutians West": {
    "dateStr": "11/25/21",
    "cases": 945,
    "deaths": 2,
    "recovered": 0,
    "new": 0,
    "newDeaths": 0
  },
  "Anchorage": {
    "dateStr": "11/25/21",
    "cases": 60818,
    "deaths": 395,
    "recovered": 0,
    "new": 0,
    "newDeaths": 0
  },
  "Bethel": {
    "dateStr": "11/25/21",
    "cases": 6679,
    "deaths": 27,
    "recovered": 0,
    "new": 0,
    "newDeaths": 0
  },
  "Bristol Bay": {
    "dateStr": "11/25/21",
    "cases": 0,
    "deaths": 0,
    "recovered": 0,
    "new": 0,
    "newDeaths": 0
  },
  "Bristol Bay plus Lake and Peninsula": {
    "dateStr": "11/25/21",
    "cases": 541,
    "deaths": 1,
    "recovered": 0,
    "new": 0,
    "newDeaths": 0
  },
  "Chugach": {
    "dateStr": "11/25/21",
    "cases": 1224,
    "deaths": 8,
    "recovered": 0,
    "new": 0,
    "newDeaths": 0
  },
  "Copper River": {
    "dateStr": "11/25/21",
    "cases": 658,
    "deaths": 2,
    "recovered": 0,
    "new": 0,
    "newDeaths": 0
  },
  "Denali": {
    "dateStr": "11/25/21",
    "cases": 293,
    "deaths": 1,
    "recovered": 0,
    "new": 0,
    "newDeaths": 0
  },
  "Dillingham": {
    "dateStr": "11/25/21",
    "cases": 943,
    "deaths": 8,
    "recovered": 0,
    "new": 0,
    "newDeaths": 0
  },
  "Fairbanks North Star": {
    "dateStr": "11/25/21",
    "cases": 17003,
    "deaths": 107,
    "recovered": 0,
    "new": 0,
    "newDeaths": 0
  },
  "Haines": {
    "dateStr": "11/25/21",
    "cases": 239,
    "deaths": 1,
    "recovered": 0,
    "new": 0,
    "newDeaths": 0
  },
  "Hoonah-Angoon": {
    "dateStr": "11/25/21",
    "cases": 0,
    "deaths": 0,
    "recovered": 0,
    "new": 0,
    "newDeaths": 0
  },
  "Juneau": {
    "dateStr": "11/25/21",
    "cases": 4137,
    "deaths": 14,
    "recovered": 0,
    "new": 0,
    "newDeaths": 0
  },
  "Kenai Peninsula": {
    "dateStr": "11/25/21",
    "cases": 11833,
    "deaths": 66,
    "recovered": 0,
    "new": 0,
    "newDeaths": 0
  },
  "Ketchikan Gateway": {
    "dateStr": "11/25/21",
    "cases": 2002,
    "deaths": 13,
    "recovered": 0,
    "new": 0,
    "newDeaths": 0
  },
  "Kodiak Island": {
    "dateStr": "11/25/21",
    "cases": 2683,
    "deaths": 9,
    "recovered": 0,
    "new": 0,
    "newDeaths": 0
  },
  "Kusilvak": {
    "dateStr": "11/25/21",
    "cases": 2202,
    "deaths": 9,
    "recovered": 0,
    "new": 0,
    "newDeaths": 0
  },
  "Matanuska-Susitna": {
    "dateStr": "11/25/21",
    "cases": 24023,
    "deaths": 148,
    "recovered": 0,
    "new": 0,
    "newDeaths": 0
  },
  "Nome": {
    "dateStr": "11/25/21",
    "cases": 2137,
    "deaths": 2,
    "recovered": 0,
    "new": 0,
    "newDeaths": 0
  },
  "North Slope": {
    "dateStr": "11/25/21",
    "cases": 2858,
    "deaths": 8,
    "recovered": 0,
    "new": 0,
    "newDeaths": 0
  },
  "Northwest Arctic": {
    "dateStr": "11/25/21",
    "cases": 2197,
    "deaths": 10,
    "recovered": 0,
    "new": 0,
    "newDeaths": 0
  },
  "Out of AK": {
    "dateStr": "11/25/21",
    "cases": 0,
    "deaths": 0,
    "recovered": 0,
    "new": 0,
    "newDeaths": 0
  },
  "Petersburg": {
    "dateStr": "11/25/21",
    "cases": 480,
    "deaths": 3,
    "recovered": 0,
    "new": 0,
    "newDeaths": 0
  },
  "Prince of Wales-Hyder": {
    "dateStr": "11/25/21",
    "cases": 592,
    "deaths": 6,
    "recovered": 0,
    "new": 0,
    "newDeaths": 0
  },
  "Sitka": {
    "dateStr": "11/25/21",
    "cases": 1229,
    "deaths": 5,
    "recovered": 0,
    "new": 0,
    "newDeaths": 0
  },
  "Skagway": {
    "dateStr": "11/25/21",
    "cases": 90,
    "deaths": 0,
    "recovered": 0,
    "new": 0,
    "newDeaths": 0
  },
  "Southeast Fairbanks": {
    "dateStr": "11/25/21",
    "cases": 1375,
    "deaths": 11,
    "recovered": 0,
    "new": 0,
    "newDeaths": 0
  },
  "Unassigned": {
    "dateStr": "11/25/21",
    "cases": 536,
    "deaths": 5,
    "recovered": 0,
    "new": 0,
    "newDeaths": 0
  },
  "Valdez-Cordova": {
    "dateStr": "11/25/21",
    "cases": 0,
    "deaths": 0,
    "recovered": 0,
    "new": 0,
    "newDeaths": 0
  },
  "Wrangell": {
    "dateStr": "11/25/21",
    "cases": 216,
    "deaths": 0,
    "recovered": 0,
    "new": 0,
    "newDeaths": 0
  },
  "Yakutat": {
    "dateStr": "11/25/21",
    "cases": 282,
    "deaths": 3,
    "recovered": 0,
    "new": 0,
    "newDeaths": 0
  },
  "Yukon-Koyukuk": {
    "dateStr": "11/25/21",
    "cases": 798,
    "deaths": 7,
    "recovered": 0,
    "new": 0,
    "newDeaths": 0
  }
}