{
  "Allen": {
    "dateStr": "2/28/22",
    "cases": 3936,
    "deaths": 46,
    "recovered": 0,
    "new": 1,
    "newDeaths": 0
  },
  "Anderson": {
    "dateStr": "2/28/22",
    "cases": 2102,
    "deaths": 27,
    "recovered": 0,
    "new": 2,
    "newDeaths": 0
  },
  "Atchison": {
    "dateStr": "2/28/22",
    "cases": 4242,
    "deaths": 34,
    "recovered": 0,
    "new": 2,
    "newDeaths": 0
  },
  "Barber": {
    "dateStr": "2/28/22",
    "cases": 1032,
    "deaths": 8,
    "recovered": 0,
    "new": 1,
    "newDeaths": 0
  },
  "Barton": {
    "dateStr": "2/28/22",
    "cases": 6470,
    "deaths": 86,
    "recovered": 0,
    "new": 2,
    "newDeaths": 0
  },
  "Bourbon": {
    "dateStr": "2/28/22",
    "cases": 4372,
    "deaths": 46,
    "recovered": 0,
    "new": 0,
    "newDeaths": 0
  },
  "Brown": {
    "dateStr": "2/28/22",
    "cases": 2669,
    "deaths": 48,
    "recovered": 0,
    "new": 2,
    "newDeaths": 0
  },
  "Butler": {
    "dateStr": "2/28/22",
    "cases": 18734,
    "deaths": 167,
    "recovered": 0,
    "new": 12,
    "newDeaths": 0
  },
  "Chase": {
    "dateStr": "2/28/22",
    "cases": 673,
    "deaths": 9,
    "recovered": 0,
    "new": 0,
    "newDeaths": 0
  },
  "Chautauqua": {
    "dateStr": "2/28/22",
    "cases": 835,
    "deaths": 17,
    "recovered": 0,
    "new": 1,
    "newDeaths": 0
  },
  "Cherokee": {
    "dateStr": "2/28/22",
    "cases": 6125,
    "deaths": 84,
    "recovered": 0,
    "new": 1,
    "newDeaths": 0
  },
  "Cheyenne": {
    "dateStr": "2/28/22",
    "cases": 659,
    "deaths": 14,
    "recovered": 0,
    "new": 0,
    "newDeaths": 0
  },
  "Clark": {
    "dateStr": "2/28/22",
    "cases": 491,
    "deaths": 7,
    "recovered": 0,
    "new": 0,
    "newDeaths": 0
  },
  "Clay": {
    "dateStr": "2/28/22",
    "cases": 1963,
    "deaths": 33,
    "recovered": 0,
    "new": 1,
    "newDeaths": 0
  },
  "Cloud": {
    "dateStr": "2/28/22",
    "cases": 2208,
    "deaths": 36,
    "recovered": 0,
    "new": 0,
    "newDeaths": 0
  },
  "Coffey": {
    "dateStr": "2/28/22",
    "cases": 2394,
    "deaths": 39,
    "recovered": 0,
    "new": 2,
    "newDeaths": 0
  },
  "Comanche": {
    "dateStr": "2/28/22",
    "cases": 439,
    "deaths": 15,
    "recovered": 0,
    "new": 0,
    "newDeaths": 0
  },
  "Cowley": {
    "dateStr": "2/28/22",
    "cases": 10042,
    "deaths": 147,
    "recovered": 0,
    "new": 1,
    "newDeaths": 0
  },
  "Crawford": {
    "dateStr": "2/28/22",
    "cases": 11806,
    "deaths": 122,
    "recovered": 0,
    "new": 11,
    "newDeaths": 1
  },
  "Decatur": {
    "dateStr": "2/28/22",
    "cases": 610,
    "deaths": 18,
    "recovered": 0,
    "new": 0,
    "newDeaths": 0
  },
  "Dickinson": {
    "dateStr": "2/28/22",
    "cases": 4780,
    "deaths": 73,
    "recovered": 0,
    "new": 5,
    "newDeaths": 0
  },
  "Doniphan": {
    "dateStr": "2/28/22",
    "cases": 2428,
    "deaths": 32,
    "recovered": 0,
    "new": 1,
    "newDeaths": 0
  },
  "Douglas": {
    "dateStr": "2/28/22",
    "cases": 25132,
    "deaths": 131,
    "recovered": 0,
    "new": 30,
    "newDeaths": 0
  },
  "Edwards": {
    "dateStr": "2/28/22",
    "cases": 560,
    "deaths": 13,
    "recovered": 0,
    "new": 0,
    "newDeaths": 0
  },
  "Elk": {
    "dateStr": "2/28/22",
    "cases": 569,
    "deaths": 8,
    "recovered": 0,
    "new": 0,
    "newDeaths": 0
  },
  "Ellis": {
    "dateStr": "2/28/22",
    "cases": 7107,
    "deaths": 80,
    "recovered": 0,
    "new": 2,
    "newDeaths": 0
  },
  "Ellsworth": {
    "dateStr": "2/28/22",
    "cases": 2017,
    "deaths": 31,
    "recovered": 0,
    "new": 0,
    "newDeaths": 0
  },
  "Finney": {
    "dateStr": "2/28/22",
    "cases": 11498,
    "deaths": 106,
    "recovered": 0,
    "new": 5,
    "newDeaths": 0
  },
  "Ford": {
    "dateStr": "2/28/22",
    "cases": 10573,
    "deaths": 108,
    "recovered": 0,
    "new": 3,
    "newDeaths": 1
  },
  "Franklin": {
    "dateStr": "2/28/22",
    "cases": 6890,
    "deaths": 77,
    "recovered": 0,
    "new": 6,
    "newDeaths": 0
  },
  "Geary": {
    "dateStr": "2/28/22",
    "cases": 9156,
    "deaths": 73,
    "recovered": 0,
    "new": 13,
    "newDeaths": 0
  },
  "Gove": {
    "dateStr": "2/28/22",
    "cases": 787,
    "deaths": 23,
    "recovered": 0,
    "new": 0,
    "newDeaths": 0
  },
  "Graham": {
    "dateStr": "2/28/22",
    "cases": 564,
    "deaths": 13,
    "recovered": 0,
    "new": 1,
    "newDeaths": 0
  },
  "Grant": {
    "dateStr": "2/28/22",
    "cases": 2191,
    "deaths": 34,
    "recovered": 0,
    "new": 2,
    "newDeaths": 0
  },
  "Gray": {
    "dateStr": "2/28/22",
    "cases": 1226,
    "deaths": 23,
    "recovered": 0,
    "new": 0,
    "newDeaths": 0
  },
  "Greeley": {
    "dateStr": "2/28/22",
    "cases": 333,
    "deaths": 3,
    "recovered": 0,
    "new": 1,
    "newDeaths": 0
  },
  "Greenwood": {
    "dateStr": "2/28/22",
    "cases": 1776,
    "deaths": 22,
    "recovered": 0,
    "new": 0,
    "newDeaths": 0
  },
  "Hamilton": {
    "dateStr": "2/28/22",
    "cases": 461,
    "deaths": 3,
    "recovered": 0,
    "new": 0,
    "newDeaths": 0
  },
  "Harper": {
    "dateStr": "2/28/22",
    "cases": 1640,
    "deaths": 25,
    "recovered": 0,
    "new": 2,
    "newDeaths": 0
  },
  "Harvey": {
    "dateStr": "2/28/22",
    "cases": 9500,
    "deaths": 117,
    "recovered": 0,
    "new": 9,
    "newDeaths": 0
  },
  "Haskell": {
    "dateStr": "2/28/22",
    "cases": 965,
    "deaths": 11,
    "recovered": 0,
    "new": 0,
    "newDeaths": 0
  },
  "Hodgeman": {
    "dateStr": "2/28/22",
    "cases": 409,
    "deaths": 10,
    "recovered": 0,
    "new": 0,
    "newDeaths": 0
  },
  "Jackson": {
    "dateStr": "2/28/22",
    "cases": 3869,
    "deaths": 27,
    "recovered": 0,
    "new": 2,
    "newDeaths": 0
  },
  "Jefferson": {
    "dateStr": "2/28/22",
    "cases": 4730,
    "deaths": 58,
    "recovered": 0,
    "new": 2,
    "newDeaths": 0
  },
  "Jewell": {
    "dateStr": "2/28/22",
    "cases": 783,
    "deaths": 13,
    "recovered": 0,
    "new": 0,
    "newDeaths": 0
  },
  "Johnson": {
    "dateStr": "2/28/22",
    "cases": 143970,
    "deaths": 1169,
    "recovered": 0,
    "new": 156,
    "newDeaths": 0
  },
  "Kearny": {
    "dateStr": "2/28/22",
    "cases": 1237,
    "deaths": 20,
    "recovered": 0,
    "new": 1,
    "newDeaths": 0
  },
  "Kingman": {
    "dateStr": "2/28/22",
    "cases": 1945,
    "deaths": 26,
    "recovered": 0,
    "new": 1,
    "newDeaths": 0
  },
  "Kiowa": {
    "dateStr": "2/28/22",
    "cases": 667,
    "deaths": 7,
    "recovered": 0,
    "new": 0,
    "newDeaths": 0
  },
  "Labette": {
    "dateStr": "2/28/22",
    "cases": 6581,
    "deaths": 72,
    "recovered": 0,
    "new": 2,
    "newDeaths": 1
  },
  "Lane": {
    "dateStr": "2/28/22",
    "cases": 294,
    "deaths": 11,
    "recovered": 0,
    "new": 0,
    "newDeaths": 0
  },
  "Leavenworth": {
    "dateStr": "2/28/22",
    "cases": 19192,
    "deaths": 174,
    "recovered": 0,
    "new": 14,
    "newDeaths": 0
  },
  "Lincoln": {
    "dateStr": "2/28/22",
    "cases": 617,
    "deaths": 9,
    "recovered": 0,
    "new": 0,
    "newDeaths": 0
  },
  "Linn": {
    "dateStr": "2/28/22",
    "cases": 2810,
    "deaths": 24,
    "recovered": 0,
    "new": 1,
    "newDeaths": 0
  },
  "Logan": {
    "dateStr": "2/28/22",
    "cases": 838,
    "deaths": 12,
    "recovered": 0,
    "new": 0,
    "newDeaths": 0
  },
  "Lyon": {
    "dateStr": "2/28/22",
    "cases": 9916,
    "deaths": 115,
    "recovered": 0,
    "new": 2,
    "newDeaths": 0
  },
  "Marion": {
    "dateStr": "2/28/22",
    "cases": 3308,
    "deaths": 39,
    "recovered": 0,
    "new": 2,
    "newDeaths": 0
  },
  "Marshall": {
    "dateStr": "2/28/22",
    "cases": 2540,
    "deaths": 41,
    "recovered": 0,
    "new": 0,
    "newDeaths": 0
  },
  "McPherson": {
    "dateStr": "2/28/22",
    "cases": 7729,
    "deaths": 124,
    "recovered": 0,
    "new": 3,
    "newDeaths": 0
  },
  "Meade": {
    "dateStr": "2/28/22",
    "cases": 1217,
    "deaths": 19,
    "recovered": 0,
    "new": 0,
    "newDeaths": 0
  },
  "Miami": {
    "dateStr": "2/28/22",
    "cases": 7687,
    "deaths": 87,
    "recovered": 0,
    "new": 7,
    "newDeaths": 1
  },
  "Mitchell": {
    "dateStr": "2/28/22",
    "cases": 1426,
    "deaths": 19,
    "recovered": 0,
    "new": 0,
    "newDeaths": 0
  },
  "Montgomery": {
    "dateStr": "2/28/22",
    "cases": 9379,
    "deaths": 140,
    "recovered": 0,
    "new": 5,
    "newDeaths": 0
  },
  "Morris": {
    "dateStr": "2/28/22",
    "cases": 1494,
    "deaths": 26,
    "recovered": 0,
    "new": 0,
    "newDeaths": 0
  },
  "Morton": {
    "dateStr": "2/28/22",
    "cases": 620,
    "deaths": 11,
    "recovered": 0,
    "new": 0,
    "newDeaths": 0
  },
  "Nemaha": {
    "dateStr": "2/28/22",
    "cases": 3226,
    "deaths": 60,
    "recovered": 0,
    "new": 1,
    "newDeaths": 0
  },
  "Neosho": {
    "dateStr": "2/28/22",
    "cases": 5102,
    "deaths": 62,
    "recovered": 0,
    "new": 1,
    "newDeaths": 0
  },
  "Ness": {
    "dateStr": "2/28/22",
    "cases": 779,
    "deaths": 18,
    "recovered": 0,
    "new": 0,
    "newDeaths": 0
  },
  "Norton": {
    "dateStr": "2/28/22",
    "cases": 2146,
    "deaths": 38,
    "recovered": 0,
    "new": 0,
    "newDeaths": 0
  },
  "Osage": {
    "dateStr": "2/28/22",
    "cases": 3888,
    "deaths": 43,
    "recovered": 0,
    "new": 3,
    "newDeaths": 0
  },
  "Osborne": {
    "dateStr": "2/28/22",
    "cases": 789,
    "deaths": 16,
    "recovered": 0,
    "new": 1,
    "newDeaths": 0
  },
  "Ottawa": {
    "dateStr": "2/28/22",
    "cases": 1192,
    "deaths": 16,
    "recovered": 0,
    "new": 2,
    "newDeaths": 0
  },
  "Out of KS": {
    "dateStr": "2/28/22",
    "cases": 0,
    "deaths": 0,
    "recovered": 0,
    "new": 0,
    "newDeaths": 0
  },
  "Pawnee": {
    "dateStr": "2/28/22",
    "cases": 2115,
    "deaths": 23,
    "recovered": 0,
    "new": 2,
    "newDeaths": 0
  },
  "Phillips": {
    "dateStr": "2/28/22",
    "cases": 1354,
    "deaths": 29,
    "recovered": 0,
    "new": 0,
    "newDeaths": 0
  },
  "Pottawatomie": {
    "dateStr": "2/28/22",
    "cases": 5675,
    "deaths": 55,
    "recovered": 0,
    "new": 2,
    "newDeaths": 0
  },
  "Pratt": {
    "dateStr": "2/28/22",
    "cases": 1918,
    "deaths": 30,
    "recovered": 0,
    "new": 0,
    "newDeaths": 0
  },
  "Rawlins": {
    "dateStr": "2/28/22",
    "cases": 678,
    "deaths": 10,
    "recovered": 0,
    "new": 0,
    "newDeaths": 0
  },
  "Reno": {
    "dateStr": "2/28/22",
    "cases": 18444,
    "deaths": 218,
    "recovered": 0,
    "new": 3,
    "newDeaths": 0
  },
  "Republic": {
    "dateStr": "2/28/22",
    "cases": 1343,
    "deaths": 15,
    "recovered": 0,
    "new": 0,
    "newDeaths": 0
  },
  "Rice": {
    "dateStr": "2/28/22",
    "cases": 2587,
    "deaths": 22,
    "recovered": 0,
    "new": 9,
    "newDeaths": 0
  },
  "Riley": {
    "dateStr": "2/28/22",
    "cases": 13212,
    "deaths": 74,
    "recovered": 0,
    "new": 0,
    "newDeaths": 0
  },
  "Rooks": {
    "dateStr": "2/28/22",
    "cases": 1349,
    "deaths": 20,
    "recovered": 0,
    "new": 0,
    "newDeaths": 0
  },
  "Rush": {
    "dateStr": "2/28/22",
    "cases": 809,
    "deaths": 18,
    "recovered": 0,
    "new": 2,
    "newDeaths": 0
  },
  "Russell": {
    "dateStr": "2/28/22",
    "cases": 1869,
    "deaths": 36,
    "recovered": 0,
    "new": 0,
    "newDeaths": 0
  },
  "Saline": {
    "dateStr": "2/28/22",
    "cases": 14038,
    "deaths": 230,
    "recovered": 0,
    "new": 3,
    "newDeaths": 0
  },
  "Scott": {
    "dateStr": "2/28/22",
    "cases": 1274,
    "deaths": 34,
    "recovered": 0,
    "new": 1,
    "newDeaths": 0
  },
  "Sedgwick": {
    "dateStr": "2/28/22",
    "cases": 144209,
    "deaths": 1240,
    "recovered": 0,
    "new": 68,
    "newDeaths": 1
  },
  "Seward": {
    "dateStr": "2/28/22",
    "cases": 6918,
    "deaths": 59,
    "recovered": 0,
    "new": 1,
    "newDeaths": 0
  },
  "Shawnee": {
    "dateStr": "2/28/22",
    "cases": 47818,
    "deaths": 561,
    "recovered": 0,
    "new": 36,
    "newDeaths": 1
  },
  "Sheridan": {
    "dateStr": "2/28/22",
    "cases": 785,
    "deaths": 18,
    "recovered": 0,
    "new": 1,
    "newDeaths": 0
  },
  "Sherman": {
    "dateStr": "2/28/22",
    "cases": 1495,
    "deaths": 19,
    "recovered": 0,
    "new": 1,
    "newDeaths": 0
  },
  "Smith": {
    "dateStr": "2/28/22",
    "cases": 642,
    "deaths": 8,
    "recovered": 0,
    "new": 0,
    "newDeaths": 0
  },
  "Stafford": {
    "dateStr": "2/28/22",
    "cases": 1130,
    "deaths": 26,
    "recovered": 0,
    "new": 1,
    "newDeaths": 0
  },
  "Stanton": {
    "dateStr": "2/28/22",
    "cases": 437,
    "deaths": 9,
    "recovered": 0,
    "new": 1,
    "newDeaths": 0
  },
  "Stevens": {
    "dateStr": "2/28/22",
    "cases": 1455,
    "deaths": 18,
    "recovered": 0,
    "new": 0,
    "newDeaths": 0
  },
  "Sumner": {
    "dateStr": "2/28/22",
    "cases": 5607,
    "deaths": 66,
    "recovered": 0,
    "new": 3,
    "newDeaths": 0
  },
  "Thomas": {
    "dateStr": "2/28/22",
    "cases": 2369,
    "deaths": 27,
    "recovered": 0,
    "new": 2,
    "newDeaths": 0
  },
  "Trego": {
    "dateStr": "2/28/22",
    "cases": 749,
    "deaths": 9,
    "recovered": 0,
    "new": 0,
    "newDeaths": 0
  },
  "Unassigned": {
    "dateStr": "2/28/22",
    "cases": 0,
    "deaths": 259,
    "recovered": 0,
    "new": 0,
    "newDeaths": 0
  },
  "Wabaunsee": {
    "dateStr": "2/28/22",
    "cases": 1623,
    "deaths": 22,
    "recovered": 0,
    "new": 1,
    "newDeaths": 0
  },
  "Wallace": {
    "dateStr": "2/28/22",
    "cases": 436,
    "deaths": 5,
    "recovered": 0,
    "new": 0,
    "newDeaths": 0
  },
  "Washington": {
    "dateStr": "2/28/22",
    "cases": 1389,
    "deaths": 20,
    "recovered": 0,
    "new": 1,
    "newDeaths": 0
  },
  "Wichita": {
    "dateStr": "2/28/22",
    "cases": 493,
    "deaths": 8,
    "recovered": 0,
    "new": 0,
    "newDeaths": 0
  },
  "Wilson": {
    "dateStr": "2/28/22",
    "cases": 2791,
    "deaths": 39,
    "recovered": 0,
    "new": 2,
    "newDeaths": 0
  },
  "Woodson": {
    "dateStr": "2/28/22",
    "cases": 788,
    "deaths": 12,
    "recovered": 0,
    "new": 0,
    "newDeaths": 0
  },
  "Wyandotte": {
    "dateStr": "2/28/22",
    "cases": 46549,
    "deaths": 459,
    "recovered": 0,
    "new": 24,
    "newDeaths": 3
  }
}