{
  "Bernalillo": {
    "dateStr": "9/9/21",
    "cases": 67666,
    "deaths": 1018,
    "recovered": 0,
    "new": 119,
    "newDeaths": 2
  },
  "Catron": {
    "dateStr": "9/9/21",
    "cases": 133,
    "deaths": 7,
    "recovered": 0,
    "new": 0,
    "newDeaths": 1
  },
  "Chaves": {
    "dateStr": "9/9/21",
    "cases": 11176,
    "deaths": 178,
    "recovered": 0,
    "new": 61,
    "newDeaths": 0
  },
  "Cibola": {
    "dateStr": "9/9/21",
    "cases": 3137,
    "deaths": 130,
    "recovered": 0,
    "new": 10,
    "newDeaths": 0
  },
  "Colfax": {
    "dateStr": "9/9/21",
    "cases": 1000,
    "deaths": 47,
    "recovered": 0,
    "new": 6,
    "newDeaths": 0
  },
  "Curry": {
    "dateStr": "9/9/21",
    "cases": 6619,
    "deaths": 93,
    "recovered": 0,
    "new": 29,
    "newDeaths": 0
  },
  "De Baca": {
    "dateStr": "9/9/21",
    "cases": 212,
    "deaths": 3,
    "recovered": 0,
    "new": 0,
    "newDeaths": 0
  },
  "Dona Ana": {
    "dateStr": "9/9/21",
    "cases": 27491,
    "deaths": 510,
    "recovered": 0,
    "new": 39,
    "newDeaths": 1
  },
  "Eddy": {
    "dateStr": "9/9/21",
    "cases": 9536,
    "deaths": 168,
    "recovered": 0,
    "new": 28,
    "newDeaths": 0
  },
  "Grant": {
    "dateStr": "9/9/21",
    "cases": 1937,
    "deaths": 45,
    "recovered": 0,
    "new": 0,
    "newDeaths": 0
  },
  "Guadalupe": {
    "dateStr": "9/9/21",
    "cases": 554,
    "deaths": 15,
    "recovered": 0,
    "new": 5,
    "newDeaths": 0
  },
  "Harding": {
    "dateStr": "9/9/21",
    "cases": 14,
    "deaths": 2,
    "recovered": 0,
    "new": 0,
    "newDeaths": 0
  },
  "Hidalgo": {
    "dateStr": "9/9/21",
    "cases": 519,
    "deaths": 10,
    "recovered": 0,
    "new": 0,
    "newDeaths": 0
  },
  "Lea": {
    "dateStr": "9/9/21",
    "cases": 11941,
    "deaths": 215,
    "recovered": 0,
    "new": 61,
    "newDeaths": 0
  },
  "Lincoln": {
    "dateStr": "9/9/21",
    "cases": 2388,
    "deaths": 24,
    "recovered": 0,
    "new": 7,
    "newDeaths": 1
  },
  "Los Alamos": {
    "dateStr": "9/9/21",
    "cases": 630,
    "deaths": 9,
    "recovered": 0,
    "new": 0,
    "newDeaths": 0
  },
  "Luna": {
    "dateStr": "9/9/21",
    "cases": 3670,
    "deaths": 92,
    "recovered": 0,
    "new": 7,
    "newDeaths": 0
  },
  "McKinley": {
    "dateStr": "9/9/21",
    "cases": 13413,
    "deaths": 489,
    "recovered": 0,
    "new": 23,
    "newDeaths": 0
  },
  "Mora": {
    "dateStr": "9/9/21",
    "cases": 232,
    "deaths": 9,
    "recovered": 0,
    "new": 2,
    "newDeaths": 1
  },
  "Otero": {
    "dateStr": "9/9/21",
    "cases": 5039,
    "deaths": 92,
    "recovered": 0,
    "new": 10,
    "newDeaths": 0
  },
  "Out of NM": {
    "dateStr": "9/9/21",
    "cases": 0,
    "deaths": 0,
    "recovered": 0,
    "new": 0,
    "newDeaths": 0
  },
  "Quay": {
    "dateStr": "9/9/21",
    "cases": 793,
    "deaths": 12,
    "recovered": 0,
    "new": 11,
    "newDeaths": 0
  },
  "Rio Arriba": {
    "dateStr": "9/9/21",
    "cases": 4280,
    "deaths": 82,
    "recovered": 0,
    "new": 6,
    "newDeaths": 0
  },
  "Roosevelt": {
    "dateStr": "9/9/21",
    "cases": 2476,
    "deaths": 64,
    "recovered": 0,
    "new": 19,
    "newDeaths": 1
  },
  "San Juan": {
    "dateStr": "9/9/21",
    "cases": 17475,
    "deaths": 521,
    "recovered": 0,
    "new": 42,
    "newDeaths": 0
  },
  "San Miguel": {
    "dateStr": "9/9/21",
    "cases": 2099,
    "deaths": 18,
    "recovered": 0,
    "new": 23,
    "newDeaths": 0
  },
  "Sandoval": {
    "dateStr": "9/9/21",
    "cases": 14014,
    "deaths": 249,
    "recovered": 0,
    "new": 22,
    "newDeaths": 1
  },
  "Santa Fe": {
    "dateStr": "9/9/21",
    "cases": 11867,
    "deaths": 158,
    "recovered": 0,
    "new": 16,
    "newDeaths": 0
  },
  "Sierra": {
    "dateStr": "9/9/21",
    "cases": 898,
    "deaths": 52,
    "recovered": 0,
    "new": 4,
    "newDeaths": 0
  },
  "Socorro": {
    "dateStr": "9/9/21",
    "cases": 1522,
    "deaths": 62,
    "recovered": 0,
    "new": 6,
    "newDeaths": 0
  },
  "Taos": {
    "dateStr": "9/9/21",
    "cases": 2098,
    "deaths": 56,
    "recovered": 0,
    "new": 2,
    "newDeaths": 0
  },
  "Torrance": {
    "dateStr": "9/9/21",
    "cases": 1119,
    "deaths": 16,
    "recovered": 0,
    "new": 6,
    "newDeaths": 0
  },
  "Unassigned": {
    "dateStr": "9/9/21",
    "cases": 4786,
    "deaths": 114,
    "recovered": 0,
    "new": 0,
    "newDeaths": 0
  },
  "Union": {
    "dateStr": "9/9/21",
    "cases": 285,
    "deaths": 10,
    "recovered": 0,
    "new": 2,
    "newDeaths": 0
  },
  "Valencia": {
    "dateStr": "9/9/21",
    "cases": 7987,
    "deaths": 130,
    "recovered": 0,
    "new": 10,
    "newDeaths": 0
  }
}