{
  "Adams": {
    "dateStr": "1/31/22",
    "cases": 4652,
    "deaths": 35,
    "recovered": 0,
    "new": 118,
    "newDeaths": 0
  },
  "Asotin": {
    "dateStr": "1/31/22",
    "cases": 4003,
    "deaths": 55,
    "recovered": 0,
    "new": 75,
    "newDeaths": 0
  },
  "Benton": {
    "dateStr": "1/31/22",
    "cases": 48484,
    "deaths": 422,
    "recovered": 0,
    "new": 2016,
    "newDeaths": 4
  },
  "Chelan": {
    "dateStr": "1/31/22",
    "cases": 18450,
    "deaths": 142,
    "recovered": 0,
    "new": 870,
    "newDeaths": 0
  },
  "Clallam": {
    "dateStr": "1/31/22",
    "cases": 9947,
    "deaths": 108,
    "recovered": 0,
    "new": 439,
    "newDeaths": 0
  },
  "Clark": {
    "dateStr": "1/31/22",
    "cases": 75527,
    "deaths": 687,
    "recovered": 0,
    "new": 1754,
    "newDeaths": 6
  },
  "Columbia": {
    "dateStr": "1/31/22",
    "cases": 528,
    "deaths": 11,
    "recovered": 0,
    "new": 16,
    "newDeaths": 0
  },
  "Cowlitz": {
    "dateStr": "1/31/22",
    "cases": 20238,
    "deaths": 307,
    "recovered": 0,
    "new": 484,
    "newDeaths": 0
  },
  "Douglas": {
    "dateStr": "1/31/22",
    "cases": 9982,
    "deaths": 55,
    "recovered": 0,
    "new": 488,
    "newDeaths": 0
  },
  "Ferry": {
    "dateStr": "1/31/22",
    "cases": 1224,
    "deaths": 20,
    "recovered": 0,
    "new": 29,
    "newDeaths": 0
  },
  "Franklin": {
    "dateStr": "1/31/22",
    "cases": 30788,
    "deaths": 193,
    "recovered": 0,
    "new": 1282,
    "newDeaths": 1
  },
  "Garfield": {
    "dateStr": "1/31/22",
    "cases": 328,
    "deaths": 7,
    "recovered": 0,
    "new": 0,
    "newDeaths": 0
  },
  "Grant": {
    "dateStr": "1/31/22",
    "cases": 23784,
    "deaths": 194,
    "recovered": 0,
    "new": 683,
    "newDeaths": 3
  },
  "Grays Harbor": {
    "dateStr": "1/31/22",
    "cases": 14677,
    "deaths": 174,
    "recovered": 0,
    "new": 533,
    "newDeaths": 2
  },
  "Island": {
    "dateStr": "1/31/22",
    "cases": 8933,
    "deaths": 59,
    "recovered": 0,
    "new": 339,
    "newDeaths": 0
  },
  "Jefferson": {
    "dateStr": "1/31/22",
    "cases": 2542,
    "deaths": 23,
    "recovered": 0,
    "new": 90,
    "newDeaths": 1
  },
  "King": {
    "dateStr": "1/31/22",
    "cases": 345785,
    "deaths": 2301,
    "recovered": 0,
    "new": 12693,
    "newDeaths": 9
  },
  "Kitsap": {
    "dateStr": "1/31/22",
    "cases": 35583,
    "deaths": 281,
    "recovered": 0,
    "new": 981,
    "newDeaths": 1
  },
  "Kittitas": {
    "dateStr": "1/31/22",
    "cases": 7906,
    "deaths": 58,
    "recovered": 0,
    "new": 168,
    "newDeaths": 0
  },
  "Klickitat": {
    "dateStr": "1/31/22",
    "cases": 3154,
    "deaths": 38,
    "recovered": 0,
    "new": 137,
    "newDeaths": 1
  },
  "Lewis": {
    "dateStr": "1/31/22",
    "cases": 15857,
    "deaths": 212,
    "recovered": 0,
    "new": 505,
    "newDeaths": 3
  },
  "Lincoln": {
    "dateStr": "1/31/22",
    "cases": 1999,
    "deaths": 27,
    "recovered": 0,
    "new": 46,
    "newDeaths": 0
  },
  "Mason": {
    "dateStr": "1/31/22",
    "cases": 10799,
    "deaths": 113,
    "recovered": 0,
    "new": 492,
    "newDeaths": 0
  },
  "Okanogan": {
    "dateStr": "1/31/22",
    "cases": 7361,
    "deaths": 109,
    "recovered": 0,
    "new": 268,
    "newDeaths": 0
  },
  "Out of WA": {
    "dateStr": "1/31/22",
    "cases": 0,
    "deaths": 0,
    "recovered": 0,
    "new": 0,
    "newDeaths": 0
  },
  "Pacific": {
    "dateStr": "1/31/22",
    "cases": 2897,
    "deaths": 44,
    "recovered": 0,
    "new": 83,
    "newDeaths": 0
  },
  "Pend Oreille": {
    "dateStr": "1/31/22",
    "cases": 2337,
    "deaths": 29,
    "recovered": 0,
    "new": 55,
    "newDeaths": 0
  },
  "Pierce": {
    "dateStr": "1/31/22",
    "cases": 175299,
    "deaths": 1161,
    "recovered": 0,
    "new": 3905,
    "newDeaths": 17
  },
  "San Juan": {
    "dateStr": "1/31/22",
    "cases": 978,
    "deaths": 1,
    "recovered": 0,
    "new": 53,
    "newDeaths": 0
  },
  "Skagit": {
    "dateStr": "1/31/22",
    "cases": 20355,
    "deaths": 167,
    "recovered": 0,
    "new": 555,
    "newDeaths": 3
  },
  "Skamania": {
    "dateStr": "1/31/22",
    "cases": 1307,
    "deaths": 10,
    "recovered": 0,
    "new": 48,
    "newDeaths": 0
  },
  "Snohomish": {
    "dateStr": "1/31/22",
    "cases": 139882,
    "deaths": 949,
    "recovered": 0,
    "new": 5328,
    "newDeaths": 12
  },
  "Spokane": {
    "dateStr": "1/31/22",
    "cases": 115132,
    "deaths": 1214,
    "recovered": 0,
    "new": 4253,
    "newDeaths": 5
  },
  "Stevens": {
    "dateStr": "1/31/22",
    "cases": 7354,
    "deaths": 120,
    "recovered": 0,
    "new": 220,
    "newDeaths": 0
  },
  "Thurston": {
    "dateStr": "1/31/22",
    "cases": 42684,
    "deaths": 312,
    "recovered": 0,
    "new": 1155,
    "newDeaths": 4
  },
  "Unassigned": {
    "dateStr": "1/31/22",
    "cases": 3412,
    "deaths": 10,
    "recovered": 0,
    "new": 15,
    "newDeaths": 0
  },
  "Wahkiakum": {
    "dateStr": "1/31/22",
    "cases": 467,
    "deaths": 5,
    "recovered": 0,
    "new": 63,
    "newDeaths": 0
  },
  "Walla Walla": {
    "dateStr": "1/31/22",
    "cases": 14088,
    "deaths": 122,
    "recovered": 0,
    "new": 721,
    "newDeaths": 0
  },
  "Whatcom": {
    "dateStr": "1/31/22",
    "cases": 33727,
    "deaths": 234,
    "recovered": 0,
    "new": 1414,
    "newDeaths": 1
  },
  "Whitman": {
    "dateStr": "1/31/22",
    "cases": 9500,
    "deaths": 86,
    "recovered": 0,
    "new": 111,
    "newDeaths": 0
  },
  "Yakima": {
    "dateStr": "1/31/22",
    "cases": 67787,
    "deaths": 686,
    "recovered": 0,
    "new": 2706,
    "newDeaths": 3
  }
}